zyme/__init__.py
zyme/zyme.py
zyme/zyme_cli.py
zyme/resources/__init__.py
zyme/resources/config.ini
zyme/resources/config.json
zyme/resources/config.toml
zyme/resources/config.yaml
zyme/resources/resource.db
zyme/resources/resource.pickle
zyme/resources/resource.png
zyme-0.1.5.dist-info/LICENSE
zyme-0.1.5.dist-info/METADATA
zyme-0.1.5.dist-info/WHEEL
zyme-0.1.5.dist-info/entry_points.txt
zyme-0.1.5.dist-info/top_level.txt
zyme-0.1.5.dist-info/RECORD
