Metadata-Version: 2.1
Name: zyme
Version: 0.1.5
Summary: placeholder
Home-page: https://github.com/Stephen-RA-King/zyme
Download-URL: https://github.com/Stephen-RA-King/zyme/archive/refs/heads/main.zip
Author: Stephen R A King
Author-email: sking.github@gmail.com
Maintainer: Stephen R A King
Maintainer-email: sking.github@gmail.com
License: MIT
Project-URL: Bug Tracker, https://github.com/Stephen-RA-King/zyme/issues
Project-URL: CI, https://github.com/Stephen-RA-King/zyme/actions
Project-URL: Documentation, https://zyme.readthedocs.io/en/latest/
Project-URL: Release Notes, https://github.com/Stephen-RA-King/zyme/releases
Project-URL: Source Code, https://github.com/Stephen-RA-King/zyme/
Keywords: utility
Platform: Any
Classifier: Development Status :: 1 - Planning
Classifier: Environment :: Console
Classifier: Intended Audience :: Developers
Classifier: Operating System :: OS Independent
Classifier: Natural Language :: English
Classifier: Programming Language :: Python :: 3
Classifier: Programming Language :: Python :: 3 :: Only
Classifier: Programming Language :: Python :: 3.9
Classifier: Programming Language :: Python :: 3.10
Classifier: Programming Language :: Python :: 3.11
Classifier: Programming Language :: Python :: 3.12
Requires-Python: >=3.9
License-File: LICENSE
Requires-Dist: pyyaml
Requires-Dist: toml
Requires-Dist: Pillow
